data_quality_checks.py
my_data_quality_library-1.2.dist-info/METADATA
my_data_quality_library-1.2.dist-info/WHEEL
my_data_quality_library-1.2.dist-info/top_level.txt
my_data_quality_library-1.2.dist-info/RECORD
