Metadata-Version: 2.1
Name: my-data-quality-library
Version: 1.2
Summary: A library for data quality checks in Databricks notebooks
Home-page: https://github.com/harun_raseed_basheer/my_data_quality_library
Author: Harun Raseed Basheer
Author-email: harun.raseed093@gmail.com
License: MIT
Classifier: Programming Language :: Python :: 3
Classifier: Operating System :: OS Independent
